daleel/__init__.py
daleel-0.1.0.dist-info/METADATA
daleel-0.1.0.dist-info/WHEEL
daleel-0.1.0.dist-info/top_level.txt
daleel-0.1.0.dist-info/RECORD
