Metadata-Version: 2.1
Name: daleel
Version: 0.1.0
Summary: A minimal PyPI project
Home-page: https://github.com/yourusername/daleel
Author: Your Name
Author-email: your.email@example.com
Classifier: Programming Language :: Python :: 3
Classifier: License :: OSI Approved :: MIT License
Classifier: Operating System :: OS Independent
Requires-Python: >=3.6
